DobotEDU/__init__.py
DobotEDU/dobotedu.py
DobotEDU/function.py
DobotEDU/pyimageom.py
DobotEDU/device/Lite.py
DobotEDU/device/M1.py
DobotEDU/device/MagicBox.py
DobotEDU/device/Magician.py
DobotEDU/device/MagicianGo.py
DobotEDU/device/__init__.py
DobotEDU/device/betago.py
DobotEDU/pause/__init__.py
DobotEDU/pause/pauselab.py
DobotEDU/pause/pauseserver.py
test/__init__.py
test/test.py
test/test_file.py
test/test_image.py
test/test_pause.py
test/test_txun.py
dobotedu-2.2.2.dist-info/LICENSE
dobotedu-2.2.2.dist-info/METADATA
dobotedu-2.2.2.dist-info/WHEEL
dobotedu-2.2.2.dist-info/top_level.txt
dobotedu-2.2.2.dist-info/RECORD
